[{"type":"constructor","stateMutability":"undefined","payable":false,"inputs":[{"type":"address","name":"iPMSetterAddress_"}]},{"type":"error","name":"CategoryAlreadySet","inputs":[]},{"type":"error","name":"InvalidCategory","inputs":[]},{"type":"error","name":"Unauthorized","inputs":[]},{"type":"error","name":"ZeroAddress","inputs":[{"type":"address","name":"newAddress"}]},{"type":"event","anonymous":false,"name":"NewCategorySet","inputs":[{"type":"string","name":"_categoryName","indexed":false},{"type":"string","name":"_categorySymbol","indexed":false},{"type":"address","name":"_categoryContractAddressPry","indexed":false},{"type":"address","name":"_categoryContractAddressSec","indexed":false}]},{"type":"function","name":"PRECISION","constant":true,"stateMutability":"view","payable":false,"inputs":[],"outputs":[{"type":"uint48","name":""}]},{"type":"function","name":"getContractAddressOf","constant":true,"stateMutability":"view","payable":false,"inputs":[{"type":"string","name":"categorySymbol"},{"type":"uint8","name":"uniqueness"}],"outputs":[{"type":"address","name":""}]},{"type":"function","name":"isIPAddress","constant":true,"stateMutability":"view","payable":false,"inputs":[{"type":"address","name":"_iPAddress"}],"outputs":[{"type":"bool","name":""}]},{"type":"function","name":"setIPCategory","constant":false,"payable":false,"inputs":[{"type":"string","name":"_categoryName"},{"type":"string","name":"_categorySymbol"}],"outputs":[]}]